setup.py
HKH_OPT.egg-info/PKG-INFO
HKH_OPT.egg-info/SOURCES.txt
HKH_OPT.egg-info/dependency_links.txt
HKH_OPT.egg-info/entry_points.txt
HKH_OPT.egg-info/namespace_packages.txt
HKH_OPT.egg-info/requires.txt
HKH_OPT.egg-info/top_level.txt
orangecontrib/__init__.py
orangecontrib/hkh_opt/__init__.py
orangecontrib/hkh_opt/widgets/Extract_domain.py
orangecontrib/hkh_opt/widgets/__init__.py
orangecontrib/hkh_opt/widgets/icons/Chatbot.svg
orangecontrib/hkh_opt/widgets/icons/DocumentEater.svg
orangecontrib/hkh_opt/widgets/icons/Embeddings.svg
orangecontrib/hkh_opt/widgets/icons/LanguageModel.svg
orangecontrib/hkh_opt/widgets/icons/TextPreprocessing.svg
orangecontrib/hkh_opt/widgets/icons/extract.png
orangecontrib/hkh_opt/widgets/widget_designer/Extract_domain.ui