Metadata-Version: 2.1
Name: HKH-OPT
Version: 0.0.10
Summary: Let's Optimize !
Home-page: 
Author: HKH
Author-email: 
Keywords: orange3 add-on
